django_swifty-0.0.104.dist-info/licenses/LICENSE
swifty/__init__.py
swifty/auth/__init__.py
swifty/auth/constants.py
swifty/auth/permissions.py
swifty/auth/token_manager.py
swifty/cache/__init__.py
swifty/cache/constants.py
swifty/cache/manager.py
swifty/contexts/__init__.py
swifty/contexts/request_context.py
swifty/expressionator/__init__.py
swifty/expressionator/manager.py
swifty/expressionator/namespace.py
swifty/logging/__init__.py
swifty/logging/config.py
swifty/logging/logger.py
swifty/middlewares/__init__.py
swifty/mongodb/__init__.py
swifty/mongodb/connector.py
swifty/mongodb/constants.py
swifty/patches/__init__.py
swifty/patches/patch_django_fields.py
swifty/patches/patch_inspect.py
swifty/redis/__init__.py
swifty/redis/cache.py
swifty/redis/constants.py
swifty/serializers/__init__.py
swifty/serializers/constants.py
swifty/serializers/dynamic_serializer.py
swifty/serializers/fields.py
swifty/serializers/manager.py
swifty/sqldb/__init__.py
swifty/sqldb/constants.py
swifty/sqldb/core.py
swifty/sqldb/session.py
swifty/utils/__init__.py
swifty/utils/decorators.py
swifty/utils/helpers.py
swifty/utils/importer.py
swifty/utils/mapper.py
swifty/utils/objects.py
swifty/viewsets/__init__.py
swifty/viewsets/constants.py
swifty/viewsets/exceptions.py
swifty/viewsets/viewsets.py
django_swifty-0.0.104.dist-info/METADATA
django_swifty-0.0.104.dist-info/WHEEL
django_swifty-0.0.104.dist-info/top_level.txt
django_swifty-0.0.104.dist-info/RECORD
