Metadata-Version: 2.4
Name: django-swifty
Version: 0.0.104
Summary: Swifty Utils for Django Application
Home-page: https://github.com/pypa/sampleproject
Author: Fudu
Author-email: hphuc3005@gmail.com
Classifier: Programming Language :: Python :: 3
Classifier: Framework :: Django
Classifier: License :: OSI Approved :: MIT License
Classifier: Operating System :: OS Independent
Requires-Python: >=3.8
License-File: LICENSE
Requires-Dist: asgiref>=3.2.2
Requires-Dist: cffi==1.17.1
Requires-Dist: cryptography==43.0.3
Requires-Dist: Django>=3.2.4
Requires-Dist: django-auxilium==0.1.4
Requires-Dist: djangorestframework>=3.12.4
Requires-Dist: djangorestframework-simplejwt==5.3.1
Requires-Dist: django-sorcery==0.13.0
Requires-Dist: django-structlog>=2.2.0
Requires-Dist: dnspython==2.7.0
Requires-Dist: mongoengine==0.29.1
Requires-Dist: pathlib==1.0.1
Requires-Dist: pycparser==2.22
Requires-Dist: PyJWT==2.9.0
Requires-Dist: pymongo==4.10.1
Requires-Dist: redis>=3.5.3
Requires-Dist: RestrictedPython==7.4
Requires-Dist: setuptools==75.3.0
Requires-Dist: six==1.16.0
Requires-Dist: SQLAlchemy==1.4.54
Requires-Dist: sqlparse>=0.2.2
Requires-Dist: structlog>=22.1.0
Requires-Dist: typing_extensions==4.12.2
Requires-Dist: tzdata==2024.2
Dynamic: author
Dynamic: author-email
Dynamic: classifier
Dynamic: description
Dynamic: description-content-type
Dynamic: home-page
Dynamic: license-file
Dynamic: requires-dist
Dynamic: requires-python
Dynamic: summary
